README.md
setup.py
maliampi/__init__.py
maliampi/maliampi.py
maliampi.egg-info/PKG-INFO
maliampi.egg-info/SOURCES.txt
maliampi.egg-info/dependency_links.txt
maliampi.egg-info/entry_points.txt
maliampi.egg-info/requires.txt
maliampi.egg-info/top_level.txt
maliampi/lib/ExtractGenbank.py
maliampi/lib/NCBI_NT_Repository.py
maliampi/lib/__init__.py
maliampi/lib/targets.py
maliampi/lib/tasks.py
maliampi/subcommands/__init__.py
maliampi/subcommands/classify.py
maliampi/subcommands/ncbi_16s.py
maliampi/subcommands/placement.py
maliampi/subcommands/refpkg.py
maliampi/subcommands/sv_dada2.py