Metadata-Version: 2.1
Name: maliampi
Version: 0.5
Summary: Maximum Likelihood Amplicon Pipeline
Home-page: https://github.com/jgolob/maliampi
Author: Jonathan Golob
Author-email: j-dev@golob.org
License: UNKNOWN
Platform: UNKNOWN
Classifier: Programming Language :: Python :: 3
Classifier: License :: OSI Approved :: MIT License
Classifier: Operating System :: OS Independent
